soundboar/__init__.py
soundboar/__main__.py
soundboar/app/__init__.py
soundboar/app/api.py
soundboar/app/api_types.py
soundboar/app/app.py
soundboar/app/websocket.html
soundboar/cli/__init__.py
soundboar/default_data/sounds/error-2.wav
soundboar/default_data/sounds/error-3.wav
soundboar/default_data/sounds/error.wav
soundboar/default_data/static/index.html
soundboar/logs.py
soundboar/player/Player.py
soundboar/player/VLCPlayer.py
soundboar/player/__init__.py
soundboar/repository/Repository.py
soundboar/repository/__init__.py
soundboar/requirements.txt
soundboar/util/CallbackToAsync.py
soundboar/util/__init__.py
soundboar/util/env.py
soundboar/util/openapi.py
soundboar-0.1.2.dist-info/METADATA
soundboar-0.1.2.dist-info/WHEEL
soundboar-0.1.2.dist-info/entry_points.txt
soundboar-0.1.2.dist-info/RECORD
